<?xml version="1.0" encoding="UTF-8"?>
<!DOCTYPE struts PUBLIC
    "-//Apache Software Foundation//DTD Struts Configuration 2.0//EN"
    "http://struts.apache.org/dtds/struts-2.3.dtd">
<struts>
	<package name="myDefault" namespace="/" extends="struts-default">
		<interceptors>
			<interceptor name="loginInterceptor" class="cn.ustc.web.interceptor.LoginInterceptor"/>
			<interceptor-stack name="myStack">
				<interceptor-ref name="defaultStack"/>
				<interceptor-ref name="loginInterceptor">
					<param name="exclude">user_login,user_register,company_register,professor_register</param>	
				</interceptor-ref>
			</interceptor-stack>
		</interceptors>
		<default-interceptor-ref name="myStack"/>
		
		<global-results>
			<result name="login">/user/login.jsp</result>
			<result name="error">/error.jsp</result>
			<result name="input">/input.jsp</result>
		</global-results>
	</package>

	<!-- 防止表单重复提交 -->
	<package name="token" namespace="/token" extends="myDefault">
		<action name="user_register" method="register" class="cn.ustc.web.action.UserAction">
			<interceptor-ref name="token"/>
			<interceptor-ref name="myStack"/>
			<result name="invalid.token">/token_error.jsp</result>
			<result name="input">/user/login.jsp</result>
			<result name="registerOK">/user/login.jsp</result>
			<result name="registerINPUT">/user/register.jsp</result>
		</action>
		<action name="company_register" method="register" class="cn.ustc.web.action.CompanyAction">
			<result name="companyRegisterSuccess">/user/login.jsp</result>
			<result name="companyRegister">/company/register.jsp</result>
		</action>
		<action name="professor_register" method="register" class="cn.ustc.web.action.ProfessorAction">
			<result name="professorRegisterSuccess">/user/login.jsp</result>
			<result name="professorRegister">/company/register.jsp</result>
		</action>
	</package>
	
	<!-- ajax 请求，返回json数据 -->
	<package name="myjson" namespace="/json" extends="json-default">
		
		<action name="checkUserName" class="cn.ustc.web.action.UserAction" method="checkUserName">
			<!-- 要点二 ：结果集类型 必须指定为 json -->
			<!-- 默认将值栈顶端对象返回，如果没有实现ModelDriven ，Action就是顶端对象 -->
			<result type="json"></result>
		</action>
		<action name="checkCompanyName" class="cn.ustc.web.action.CompanyAction" method="checkCompanyName">
			<result type="json">
				<param name="ignoreHierarchy" >false</param>  
			</result>
		</action>
		<action name="checkProfessorName" class="cn.ustc.web.action.ProfessorAction" method="checkProfessorName">
			<result type="json">
				<param name="ignoreHierarchy" >false</param>  
			</result>
		</action>
		<action name="listVocation" class="cn.ustc.web.action.ListVocation" method="list">
			<result type="json"></result>
		</action>
		<action name="getMyUnreadMessageCount" class="cn.ustc.web.action.MessageAction" method="getMyUnreadMessageCount">
			<result type="json"></result>
		</action>
		<action name="queryMyConsultReturnJson" class="cn.ustc.web.action.ConsultAction" method="queryMyConsultReturnJson">
			<result type="json">
				<param name="root">action</param>
			</result>
		</action>
		
	</package>
	
	<package name="consult" namespace="/consult" extends="myDefault">
		<action name="consult_*" method="{1}" class="cn.ustc.web.action.ConsultAction">
			<result name="publishSUCCESS">/success.jsp</result>
			<result name="listSUCCESS">/project/consult_list.jsp</result>
			<result name="allowListSUCCESS">/project/consult_recieve.jsp</result>
			<result name="viewSUCCESS">/project/consultInfo.jsp</result>
			<result name="queryMyConsultSUCCESS">/company/company_consults.jsp</result>
			
			<result name="checkSUCCESS" type="redirectAction">consult_unCheckList</result>
			<result name="checkFAIL" type="redirectAction">consult_unCheckList</result>
			<result name="unCheckListSUCCESS">/project/consult_unCheckList.jsp</result>
			
			<result name="downSUCCESS" type="stream">
				<!-- 下载流 getInputStream -->
				<param name="contentType">${contentType}</param>
				<param name="contentDisposition">attachment;filename=${downloadFileName}</param>
			</result>
		</action>
	</package>
	
	<package name="scheme" namespace="/scheme" extends="myDefault">
		<action name="scheme_*" method="{1}" class="cn.ustc.web.action.SchemeAction">
			<result name="submitViewSUCCESS">/scheme/scheme_publish.jsp</result>
			<result name="publishSUCCESS" type="redirectAction">
				<param name="namespace">/consult</param>
				<param name="actionName">consult_allowList</param>
			</result>
			<result name="listSUCCESS">/scheme/scheme_list.jsp</result>
			<!-- <result name="viewSUCCESS">/scheme/schemeInfo.jsp</result> -->
			<result name="queryMySchemeSUCCESS">/scheme/professorscheme_list.jsp</result>
			<result name="findConsultSchemesSUCCESS">/company/consult_schemes.jsp</result>
			<result name="findProjectSchemeSUCCESS">/scheme/scheme_Info.jsp</result>
			
			<result name="downSUCCESS" type="stream">
				<!-- 下载流 getInputStream -->
				<param name="contentType">${contentType}</param>
				<param name="contentDisposition">attachment;filename=${downloadFileName}</param>
			</result>
		</action>
	</package>
	
	<package name="project" namespace="/project" extends="myDefault">
		<action name="project_*" method="{1}" class="cn.ustc.web.action.ProjectAction">
			<result name="queryMyProjectSUCCESS">/project/project_list.jsp</result>
			<result name="completeSUCCESS" type="redirectAction">project_queryMyProject</result>
						
			<result name="downSUCCESS" type="stream">
				<!-- 下载流 getInputStream -->
				<param name="contentType">${contentType}</param>
				<param name="contentDisposition">attachment;filename=${downloadFileName}</param>
			</result>
		</action>
	</package>
	
	<package name="evaluate" namespace="/evaluate" extends="myDefault">
		<action name="evaluate_*" method="{1}" class="cn.ustc.web.action.EvaluateAction">
			<result name="publishView">/project/evaluate_publish.jsp</result>
						
			<result name="downSUCCESS" type="stream">
				<!-- 下载流 getInputStream -->
				<param name="contentType">${contentType}</param>
				<param name="contentDisposition">attachment;filename=${downloadFileName}</param>
			</result>
		</action>
	</package>
	
	<package name="company" namespace="/company" extends="myDefault">
		<action name="company_*" method="{1}" class="cn.ustc.web.action.CompanyAction">
			<result name="skipBalancePageSUCCESS">/company/company_balance.jsp</result>
			<result name="addBalanceSUCCESS" type="redirectAction">
				<param name="actionName">company_skipBalancePage</param>
				<param name="namespace">/company</param>
			</result>
		</action>
	</package>
	
	<package name="message" namespace="/message" extends="myDefault">
		<action name="message_*" method="{1}" class="cn.ustc.web.action.MessageAction">
			<result name="queryMyUnreadSUCCESS">/message/message_list.jsp</result>
			<result name="haveReadedSUCCESS" type="redirectAction">
				<param name="actionName">message_queryMyUnread</param>
				<param name="namespace">/message</param>
			</result>
		</action>
	</package>
	
</struts>
